LICENSE.md
replacy_article_agreer/__init__.py
replacy_article_agreer/article.py
replacy_article_agreer-0.2.2.dist-info/LICENSE.md
replacy_article_agreer-0.2.2.dist-info/WHEEL
replacy_article_agreer-0.2.2.dist-info/METADATA
replacy_article_agreer-0.2.2.dist-info/RECORD
